{
  "type": "FeatureCollection", 
  "features": [
    {
      "geometry": {
        "type": "Polygon", 
        "coordinates": [
          [
            [
              1.397480, 
              43.642071
            ], 
            [
              1.397454, 
              43.642066
            ], 
            [
              1.397469, 
              43.642031
            ], 
            [
              1.397494, 
              43.642037
            ], 
            [
              1.397480, 
              43.642071
            ], 
            [
              1.397480, 
              43.642071
            ]
          ]
        ]
      }, 
      "id": 2158677337, 
      "properties": {
        "osm:way_id": 64419389, 
        "woe:parent": "125128856", 
        "tags": [
          "source=cadastre-dgi-fr source 8c Direction G\u00e9n\u00e9rale des Imp\u00f4ts - Cadastre. Mise \u00e0 jour 8c 2010"
        ], 
        "hierarchy": [
          "woe:airport=12512856", 
          "woe:localadmin=12657137", 
          "woe:county=12597186", 
          "woe:state=7153323", 
          "woe:country=23424819", 
          "woe:planet=1"
        ], 
        "parent_woeid": 12512856, 
        "osm:node_ids": [
          792437255, 
          792473798, 
          792441001, 
          792483640, 
          792437255
        ], 
        "ne_longitude": 1.397494, 
        "longitude": 43.642052, 
        "sw_longitude": 1.397454, 
        "woe:placetype": "building", 
        "ne_latitude": 43.642071, 
        "latitude": 1.397475, 
        "iso": "FR", 
        "woe:id": 2158677337, 
        "sw_latitude": 43.642031
      }
    }
  ]
}