{
  "type": "FeatureCollection", 
  "features": [
    {
      "geometry": {
        "type": "Polygon", 
        "coordinates": [
          [
            [
              15.776172, 
              52.142598
            ], 
            [
              15.776271, 
              52.142514
            ], 
            [
              15.776414, 
              52.142577
            ], 
            [
              15.776315, 
              52.142661
            ], 
            [
              15.776172, 
              52.142598
            ], 
            [
              15.776172, 
              52.142598
            ]
          ]
        ]
      }, 
      "id": 2156140348, 
      "properties": {
        "tags": [
          "addr:housenumber=5", 
          "addr:postcode=66-111", 
          "addr:street=Grunwaldzka"
        ], 
        "hierarchy": [
          "woe:airport=12515279", 
          "woe:localadmin=24547928", 
          "woe:county=12591247", 
          "woe:state=12577939", 
          "woe:country=23424923", 
          "woe:planet=1"
        ], 
        "sw_latitude": 52.142514, 
        "osm:node_ids": [
          738259241, 
          738259376, 
          738259121, 
          738259164, 
          738259241
        ], 
        "ne_longitude": 15.776414, 
        "longitude": 52.142588, 
        "sw_longitude": 15.776172, 
        "woe:placetype": "building", 
        "ne_latitude": 52.142661, 
        "latitude": 15.776294, 
        "iso": "PL", 
        "woe:id": 2156140348, 
        "osm:way_id": 59531740
      }
    }
  ]
}