{
  "type": "FeatureCollection", 
  "features": [
    {
      "geometry": {
        "type": "Polygon", 
        "coordinates": [
          [
            [
              2.449380, 
              48.947361
            ], 
            [
              2.449321, 
              48.947274
            ], 
            [
              2.449361, 
              48.947260
            ], 
            [
              2.449419, 
              48.947349
            ], 
            [
              2.449380, 
              48.947361
            ], 
            [
              2.449380, 
              48.947361
            ]
          ]
        ]
      }, 
      "id": 2169352457, 
      "properties": {
        "osm:way_id": 84298638, 
        "woe:parent": "22137770", 
        "tags": [
          "note:import-bati=v0.3", 
          "source=cadastre-dgi-fr source 8c Direction G\u00e9n\u00e9rale des Imp\u00f4ts - Cadastre. Mise \u00e0 jour 8c 2010"
        ], 
        "hierarchy": "woe:country=234248819", 
        "parent_woeid": 22137770, 
        "osm:node_ids": [
          980151087, 
          980137658, 
          980111137, 
          980153321, 
          980151087
        ], 
        "ne_longitude": 2.449419, 
        "longitude": 48.947311, 
        "ne_latitude": 48.947361, 
        "woe:placetype": "building", 
        "sw_longitude": 2.449321, 
        "latitude": 2.449370, 
        "woe:id": 2169352457, 
        "sw_latitude": 48.947260
      }
    }
  ]
}