{
  "type": "FeatureCollection", 
  "features": [
    {
      "geometry": {
        "type": "Polygon", 
        "coordinates": [
          [
            [
              1.375465, 
              43.646781
            ], 
            [
              1.375444, 
              43.646775
            ], 
            [
              1.375452, 
              43.646758
            ], 
            [
              1.375472, 
              43.646763
            ], 
            [
              1.375465, 
              43.646781
            ], 
            [
              1.375465, 
              43.646781
            ]
          ]
        ]
      }, 
      "id": 2158681149, 
      "properties": {
        "osm:way_id": 64423291, 
        "woe:parent": "125128856", 
        "tags": [
          "wall=no", 
          "source=cadastre-dgi-fr source 8c Direction G\u00e9n\u00e9rale des Imp\u00f4ts - Cadastre. Mise \u00e0 jour 8c 2010"
        ], 
        "hierarchy": [
          "woe:airport=12512856", 
          "woe:localadmin=12657137", 
          "woe:county=12597186", 
          "woe:state=7153323", 
          "woe:country=23424819", 
          "woe:planet=1"
        ], 
        "parent_woeid": 12512856, 
        "osm:node_ids": [
          792427599, 
          792388903, 
          792385690, 
          792486194, 
          792427599
        ], 
        "ne_longitude": 1.375472, 
        "longitude": 43.646770, 
        "sw_longitude": 1.375444, 
        "woe:placetype": "building", 
        "ne_latitude": 43.646781, 
        "latitude": 1.375458, 
        "iso": "FR", 
        "woe:id": 2158681149, 
        "sw_latitude": 43.646758
      }
    }
  ]
}