{
  "type": "FeatureCollection", 
  "features": [
    {
      "geometry": {
        "type": "Polygon", 
        "coordinates": [
          [
            [
              13.816558, 
              51.164077
            ], 
            [
              13.816688, 
              51.164129
            ], 
            [
              13.816599, 
              51.164208
            ], 
            [
              13.816473, 
              51.164156
            ], 
            [
              13.816558, 
              51.164077
            ], 
            [
              13.816558, 
              51.164077
            ]
          ]
        ]
      }, 
      "id": 2153243896, 
      "properties": {
        "woe:parent": "12513205", 
        "hierarchy": [
          "woe:airport=12513205", 
          "woe:country=234248829"
        ], 
        "parent_woeid": 12513205, 
        "sw_latitude": 51.164077, 
        "osm:node_ids": [
          667830412, 
          667830415, 
          667830416, 
          667830418, 
          667830412
        ], 
        "ne_longitude": 13.816688, 
        "longitude": 51.164143, 
        "sw_longitude": 13.816473, 
        "woe:placetype": "building", 
        "ne_latitude": 51.164208, 
        "latitude": 13.816580, 
        "woe:id": 2153243896, 
        "osm:way_id": 52565660
      }
    }
  ]
}