{
  "type": "FeatureCollection", 
  "features": [
    {
      "geometry": {
        "type": "Polygon", 
        "coordinates": [
          [
            [
              2.398245, 
              48.731905
            ], 
            [
              2.398251, 
              48.731851
            ], 
            [
              2.398289, 
              48.731852
            ], 
            [
              2.398285, 
              48.731905
            ], 
            [
              2.398245, 
              48.731905
            ], 
            [
              2.398245, 
              48.731905
            ]
          ]
        ]
      }, 
      "id": 2162602682, 
      "properties": {
        "tags": [
          "source=extraction vectorielle v1 cadastre-dgi-fr source 8c Direction G\u00e9n\u00e9rale des Imp\u00f4ts - Cadas. Mise \u00e0 jour 8c 2010"
        ], 
        "hierarchy": [
          "woe:airport=22144181", 
          "woe:localadmin=12636789", 
          "woe:county=12597118", 
          "woe:state=7153319", 
          "woe:country=23424819", 
          "woe:planet=1"
        ], 
        "sw_latitude": 48.731851, 
        "osm:node_ids": [
          844802458, 
          844745091, 
          844817360, 
          844797751, 
          844802458
        ], 
        "ne_longitude": 2.398289, 
        "longitude": 48.731879, 
        "sw_longitude": 2.398245, 
        "woe:placetype": "building", 
        "ne_latitude": 48.731905, 
        "latitude": 2.398268, 
        "iso": "FR", 
        "woe:id": 2162602682, 
        "osm:way_id": 70865928
      }
    }
  ]
}