{
  "type": "FeatureCollection", 
  "features": [
    {
      "geometry": {
        "type": "Polygon", 
        "coordinates": [
          [
            [
              -2.212773, 
              57.199925
            ], 
            [
              -2.212762, 
              57.199826
            ], 
            [
              -2.211507, 
              57.199785
            ], 
            [
              -2.211507, 
              57.199878
            ], 
            [
              -2.212773, 
              57.199925
            ], 
            [
              -2.212773, 
              57.199925
            ]
          ]
        ]
      }, 
      "id": 2152895198, 
      "properties": {
        "hierarchy": [
          "woe:airport=22450858", 
          "woe:localadmin=12696182", 
          "woe:county=12602202", 
          "woe:state=12578048", 
          "woe:country=23424975", 
          "woe:planet=1"
        ], 
        "sw_latitude": 57.199785, 
        "osm:node_ids": [
          661561029, 
          661561031, 
          661561033, 
          661561035, 
          661561029
        ], 
        "ne_longitude": -2.211507, 
        "longitude": 57.199854, 
        "sw_longitude": -2.212773, 
        "woe:placetype": "building", 
        "ne_latitude": 57.199925, 
        "latitude": -2.212144, 
        "iso": "GB", 
        "woe:id": 2152895198, 
        "osm:way_id": 51856033
      }
    }
  ]
}