{
  "type": "FeatureCollection", 
  "features": [
    {
      "geometry": {
        "type": "Polygon", 
        "coordinates": [
          [
            [
              -121.244579, 
              37.893068
            ], 
            [
              -121.244390, 
              37.892993
            ], 
            [
              -121.244639, 
              37.892614
            ], 
            [
              -121.244811, 
              37.892695
            ], 
            [
              -121.244579, 
              37.893068
            ], 
            [
              -121.244579, 
              37.893068
            ]
          ]
        ]
      }, 
      "id": 2147583897, 
      "properties": {
        "osm:way_id": 25129052, 
        "woe:parent": "125220188", 
        "tags": [
          "created_by=Potlatch 0.9c"
        ], 
        "hierarchy": [
          "woe:airport=12522018", 
          "woe:suburb=2466422", 
          "woe:county=12587708", 
          "woe:state=2347563", 
          "woe:country=23424977", 
          "woe:planet=1"
        ], 
        "parent_woeid": 12522018, 
        "osm:node_ids": [
          273729560, 
          273729561, 
          273729562, 
          273729563, 
          273729560
        ], 
        "ne_longitude": -121.244390, 
        "longitude": 37.892845, 
        "sw_longitude": -121.244811, 
        "woe:placetype": "building", 
        "ne_latitude": 37.893068, 
        "latitude": -121.244604, 
        "iso": "US", 
        "woe:id": 2147583897, 
        "sw_latitude": 37.892614
      }
    }
  ]
}