{
  "type": "FeatureCollection", 
  "features": [
    {
      "geometry": {
        "type": "Polygon", 
        "coordinates": [
          [
            [
              1.339861, 
              43.612935
            ], 
            [
              1.339853, 
              43.612877
            ], 
            [
              1.339936, 
              43.612871
            ], 
            [
              1.339936, 
              43.612863
            ], 
            [
              1.339984, 
              43.612860
            ], 
            [
              1.339985, 
              43.612868
            ], 
            [
              1.340022, 
              43.612866
            ], 
            [
              1.340023, 
              43.612876
            ], 
            [
              1.340056, 
              43.612873
            ], 
            [
              1.340060, 
              43.612901
            ], 
            [
              1.340044, 
              43.612902
            ], 
            [
              1.340027, 
              43.612903
            ], 
            [
              1.340035, 
              43.612953
            ], 
            [
              1.340037, 
              43.612964
            ], 
            [
              1.340020, 
              43.612973
            ], 
            [
              1.340009, 
              43.612965
            ], 
            [
              1.339928, 
              43.612971
            ], 
            [
              1.339893, 
              43.612974
            ], 
            [
              1.339867, 
              43.612975
            ], 
            [
              1.339861, 
              43.612935
            ], 
            [
              1.339861, 
              43.612935
            ]
          ]
        ]
      }, 
      "id": 2165028367, 
      "properties": {
        "osm:way_id": 75004162, 
        "woe:parent": "125128856", 
        "tags": [
          "source=cadastre-dgi-fr source 8c Direction G\u00e9n\u00e9rale des Imp\u00f4ts - Cadastre. Mise \u00e0 jour 8c 2010"
        ], 
        "hierarchy": [
          "woe:airport=12512856", 
          "woe:localadmin=12657137", 
          "woe:county=12597186", 
          "woe:state=7153323", 
          "woe:country=23424819", 
          "woe:planet=1"
        ], 
        "parent_woeid": 12512856, 
        "osm:node_ids": [
          885561793, 
          885561369, 
          885561590, 
          885561225, 
          885561749, 
          885560457, 
          885561342, 
          885561337, 
          885561868, 
          885560600, 
          885561529, 
          885561750, 
          885560884, 
          885561930, 
          885562006, 
          885561027, 
          885560790, 
          885560656, 
          885562081, 
          885561793
        ], 
        "ne_longitude": 1.340060, 
        "longitude": 43.612918, 
        "sw_longitude": 1.339853, 
        "woe:placetype": "building", 
        "ne_latitude": 43.612975, 
        "latitude": 1.339950, 
        "iso": "FR", 
        "woe:id": 2165028367, 
        "sw_latitude": 43.612860
      }
    }
  ]
}