{
  "type": "FeatureCollection", 
  "features": [
    {
      "geometry": {
        "type": "Polygon", 
        "coordinates": [
          [
            [
              13.807247, 
              51.184788
            ], 
            [
              13.807141, 
              51.184677
            ], 
            [
              13.806899, 
              51.184768
            ], 
            [
              13.807005, 
              51.184879
            ], 
            [
              13.807247, 
              51.184788
            ], 
            [
              13.807247, 
              51.184788
            ]
          ]
        ]
      }, 
      "id": 2148304261, 
      "properties": {
        "woe:parent": "12513205", 
        "hierarchy": [
          "woe:airport=12513205", 
          "woe:country=234248829"
        ], 
        "parent_woeid": 12513205, 
        "sw_latitude": 51.184677, 
        "osm:node_ids": [
          343640446, 
          343640447, 
          343640448, 
          343640449, 
          343640446
        ], 
        "ne_longitude": 13.807247, 
        "longitude": 51.184778, 
        "sw_longitude": 13.806899, 
        "woe:placetype": "building", 
        "ne_latitude": 51.184879, 
        "latitude": 13.807074, 
        "woe:id": 2148304261, 
        "osm:way_id": 30911914
      }
    }
  ]
}