{
  "type": "FeatureCollection", 
  "features": [
    {
      "geometry": {
        "type": "Polygon", 
        "coordinates": [
          [
            [
              4.760397, 
              52.351385
            ], 
            [
              4.760243, 
              52.351466
            ], 
            [
              4.760379, 
              52.351563
            ], 
            [
              4.760472, 
              52.351514
            ], 
            [
              4.760412, 
              52.351472
            ], 
            [
              4.760474, 
              52.351439
            ], 
            [
              4.760397, 
              52.351385
            ], 
            [
              4.760397, 
              52.351385
            ]
          ]
        ]
      }, 
      "id": 2151593521, 
      "properties": {
        "tags": [
          "source=3dShapes", 
          "3dshapes:ggmodelk=2"
        ], 
        "hierarchy": [
          "woe:airport=22386730", 
          "woe:county=12592184", 
          "woe:state=2346379", 
          "woe:country=23424909", 
          "woe:planet=1"
        ], 
        "sw_latitude": 52.351385, 
        "osm:node_ids": [
          617704049, 
          617704060, 
          617704051, 
          617704054, 
          617704056, 
          617704058, 
          617704049
        ], 
        "ne_longitude": 4.760474, 
        "longitude": 52.351474, 
        "sw_longitude": 4.760243, 
        "woe:placetype": "building", 
        "ne_latitude": 52.351563, 
        "latitude": 4.760371, 
        "iso": "NL", 
        "woe:id": 2151593521, 
        "osm:way_id": 48643856
      }
    }
  ]
}