{
  "type": "FeatureCollection", 
  "features": [
    {
      "geometry": {
        "type": "Polygon", 
        "coordinates": [
          [
            [
              2.420653, 
              48.940339
            ], 
            [
              2.420789, 
              48.940290
            ], 
            [
              2.420809, 
              48.940314
            ], 
            [
              2.420821, 
              48.940310
            ], 
            [
              2.420866, 
              48.940365
            ], 
            [
              2.420767, 
              48.940400
            ], 
            [
              2.420757, 
              48.940388
            ], 
            [
              2.420710, 
              48.940405
            ], 
            [
              2.420709, 
              48.940404
            ], 
            [
              2.420677, 
              48.940415
            ], 
            [
              2.420654, 
              48.940388
            ], 
            [
              2.420685, 
              48.940377
            ], 
            [
              2.420653, 
              48.940339
            ], 
            [
              2.420653, 
              48.940339
            ]
          ]
        ]
      }, 
      "id": 2167813844, 
      "properties": {
        "tags": [
          "source=extraction vectorielle v1 cadastre-dgi-fr source 8c Direction G\u00e9n\u00e9rale des Imp\u00f4ts - Cadas. Mise \u00e0 jour 8c 2010"
        ], 
        "hierarchy": [
          "woe:airport=22137770", 
          "woe:localadmin=12643124", 
          "woe:county=12597156", 
          "woe:state=7153319", 
          "woe:country=23424819", 
          "woe:planet=1"
        ], 
        "sw_latitude": 48.940290, 
        "osm:node_ids": [
          946010984, 
          946008529, 
          946006166, 
          946009587, 
          946005385, 
          946006833, 
          946005311, 
          946004048, 
          946010809, 
          946004663, 
          946006497, 
          946012112, 
          946010984
        ], 
        "ne_longitude": 2.420866, 
        "longitude": 48.940354, 
        "sw_longitude": 2.420653, 
        "woe:placetype": "building", 
        "ne_latitude": 48.940415, 
        "latitude": 2.420754, 
        "iso": "FR", 
        "woe:id": 2167813844, 
        "osm:way_id": 81190089
      }
    }
  ]
}