{
  "type": "FeatureCollection", 
  "features": [
    {
      "geometry": {
        "type": "Polygon", 
        "coordinates": [
          [
            [
              -119.857454, 
              34.416356
            ], 
            [
              -119.857157, 
              34.416351
            ], 
            [
              -119.857161, 
              34.416236
            ], 
            [
              -119.857457, 
              34.416242
            ], 
            [
              -119.857454, 
              34.416356
            ], 
            [
              -119.857454, 
              34.416356
            ]
          ]
        ]
      }, 
      "id": 2149864017, 
      "properties": {
        "hierarchy": [
          "woe:airport=12521741", 
          "woe:county=12587711", 
          "woe:state=2347563", 
          "woe:country=23424977", 
          "woe:planet=1"
        ], 
        "sw_latitude": 34.416236, 
        "osm:node_ids": [
          534644480, 
          534644483, 
          534644482, 
          534644481, 
          534644480
        ], 
        "ne_longitude": -119.857157, 
        "longitude": 34.416297, 
        "sw_longitude": -119.857457, 
        "woe:placetype": "building", 
        "ne_latitude": 34.416356, 
        "latitude": -119.857308, 
        "iso": "US", 
        "woe:id": 2149864017, 
        "osm:way_id": 42754993
      }
    }
  ]
}