{
  "type": "FeatureCollection", 
  "features": [
    {
      "geometry": {
        "type": "Polygon", 
        "coordinates": [
          [
            [
              1.378276, 
              43.642573
            ], 
            [
              1.378270, 
              43.642585
            ], 
            [
              1.378261, 
              43.642587
            ], 
            [
              1.378251, 
              43.642585
            ], 
            [
              1.378258, 
              43.642569
            ], 
            [
              1.378276, 
              43.642573
            ], 
            [
              1.378276, 
              43.642573
            ]
          ]
        ]
      }, 
      "id": 2158670691, 
      "properties": {
        "osm:way_id": 64412554, 
        "woe:parent": "125128856", 
        "tags": [
          "wall=no", 
          "source=cadastre-dgi-fr source 8c Direction G\u00e9n\u00e9rale des Imp\u00f4ts - Cadastre. Mise \u00e0 jour 8c 2010"
        ], 
        "hierarchy": [
          "woe:airport=12512856", 
          "woe:localadmin=12657137", 
          "woe:county=12597186", 
          "woe:state=7153323", 
          "woe:country=23424819", 
          "woe:planet=1"
        ], 
        "parent_woeid": 12512856, 
        "osm:node_ids": [
          792476297, 
          792384358, 
          792447138, 
          792412979, 
          792468236, 
          792476297
        ], 
        "ne_longitude": 1.378276, 
        "longitude": 43.642579, 
        "sw_longitude": 1.378251, 
        "woe:placetype": "building", 
        "ne_latitude": 43.642587, 
        "latitude": 1.378264, 
        "iso": "FR", 
        "woe:id": 2158670691, 
        "sw_latitude": 43.642569
      }
    }
  ]
}