{
  "type": "FeatureCollection", 
  "features": [
    {
      "geometry": {
        "type": "Polygon", 
        "coordinates": [
          [
            [
              13.834824, 
              51.182985
            ], 
            [
              13.835008, 
              51.183065
            ], 
            [
              13.835128, 
              51.182952
            ], 
            [
              13.834940, 
              51.182870
            ], 
            [
              13.834824, 
              51.182985
            ], 
            [
              13.834824, 
              51.182985
            ]
          ]
        ]
      }, 
      "id": 2149423545, 
      "properties": {
        "hierarchy": [
          "woe:airport=12513205", 
          "woe:localadmin=12636478", 
          "woe:county=12597039", 
          "woe:state=2345493", 
          "woe:country=23424829", 
          "woe:planet=1"
        ], 
        "sw_latitude": 51.182870, 
        "osm:node_ids": [
          474514755, 
          474514793, 
          474514795, 
          474514757, 
          474514755
        ], 
        "ne_longitude": 13.835128, 
        "longitude": 51.182968, 
        "sw_longitude": 13.834824, 
        "woe:placetype": "building", 
        "ne_latitude": 51.183065, 
        "latitude": 13.834976, 
        "iso": "DE", 
        "woe:id": 2149423545, 
        "osm:way_id": 39586181
      }
    }
  ]
}