{
  "type": "FeatureCollection", 
  "features": [
    {
      "geometry": {
        "type": "Polygon", 
        "coordinates": [
          [
            [
              -89.675238, 
              40.675849
            ], 
            [
              -89.675240, 
              40.675911
            ], 
            [
              -89.675169, 
              40.675912
            ], 
            [
              -89.675167, 
              40.675851
            ], 
            [
              -89.675238, 
              40.675849
            ], 
            [
              -89.675238, 
              40.675849
            ]
          ]
        ]
      }, 
      "id": 2159725026, 
      "properties": {
        "osm:way_id": 65863450, 
        "woe:parent": "125199882", 
        "tags": [
          "tiger:buildingType=4"
        ], 
        "hierarchy": "woe:country=23424977", 
        "parent_woeid": 12519982, 
        "osm:node_ids": [
          801523358, 
          801514794, 
          801508399, 
          801533692, 
          801523358
        ], 
        "ne_longitude": -89.675167, 
        "longitude": 40.675881, 
        "ne_latitude": 40.675912, 
        "woe:placetype": "building", 
        "sw_longitude": -89.675240, 
        "latitude": -89.675204, 
        "woe:id": 2159725026, 
        "sw_latitude": 40.675849
      }
    }
  ]
}