{
  "type": "FeatureCollection", 
  "features": [
    {
      "geometry": {
        "type": "Polygon", 
        "coordinates": [
          [
            [
              -4.411656, 
              48.444619
            ], 
            [
              -4.411692, 
              48.444595
            ], 
            [
              -4.411791, 
              48.444669
            ], 
            [
              -4.411785, 
              48.444672
            ], 
            [
              -4.411749, 
              48.444690
            ], 
            [
              -4.411656, 
              48.444619
            ], 
            [
              -4.411656, 
              48.444619
            ]
          ]
        ]
      }, 
      "id": 2149815650, 
      "properties": {
        "tags": [
          "bmo:type=L", 
          "source=Brest Metropole Oceane, 2009"
        ], 
        "hierarchy": [
          "woe:airport=12523072", 
          "woe:localadmin=12641875", 
          "woe:county=12591797", 
          "woe:state=7153313", 
          "woe:country=23424819", 
          "woe:planet=1"
        ], 
        "sw_latitude": 48.444595, 
        "osm:node_ids": [
          532141868, 
          532141826, 
          532141824, 
          532141870, 
          532141872, 
          532141868
        ], 
        "ne_longitude": -4.411656, 
        "longitude": 48.444644, 
        "sw_longitude": -4.411791, 
        "woe:placetype": "building", 
        "ne_latitude": 48.444690, 
        "latitude": -4.411723, 
        "iso": "FR", 
        "woe:id": 2149815650, 
        "osm:way_id": 42593395
      }
    }
  ]
}