{
  "type": "FeatureCollection", 
  "features": [
    {
      "geometry": {
        "type": "Polygon", 
        "coordinates": [
          [
            [
              2.224625, 
              48.777577
            ], 
            [
              2.224606, 
              48.777595
            ], 
            [
              2.224623, 
              48.777603
            ], 
            [
              2.224560, 
              48.777663
            ], 
            [
              2.224548, 
              48.777658
            ], 
            [
              2.224491, 
              48.777636
            ], 
            [
              2.224480, 
              48.777631
            ], 
            [
              2.224568, 
              48.777551
            ], 
            [
              2.224610, 
              48.777570
            ], 
            [
              2.224625, 
              48.777577
            ], 
            [
              2.224625, 
              48.777577
            ]
          ]
        ]
      }, 
      "id": 2163114272, 
      "properties": {
        "tags": [
          "source=extraction vectorielle v1 cadastre-dgi-fr source 8c Direction G\u00e9n\u00e9rale des Imp\u00f4ts - Cadas. Mise \u00e0 jour 8c 2010"
        ], 
        "hierarchy": [
          "woe:airport=56051751", 
          "woe:localadmin=12638922", 
          "woe:county=12597118", 
          "woe:state=7153319", 
          "woe:country=23424819", 
          "woe:planet=1"
        ], 
        "sw_latitude": 48.777551, 
        "osm:node_ids": [
          852542941, 
          852556138, 
          852533231, 
          852548692, 
          852559950, 
          852554449, 
          852556949, 
          852529936, 
          852564492, 
          852542941
        ], 
        "ne_longitude": 2.224625, 
        "longitude": 48.777609, 
        "sw_longitude": 2.224480, 
        "woe:placetype": "building", 
        "ne_latitude": 48.777663, 
        "latitude": 2.224559, 
        "iso": "FR", 
        "woe:id": 2163114272, 
        "osm:way_id": 71715534
      }
    }
  ]
}