{
  "type": "FeatureCollection", 
  "features": [
    {
      "geometry": {
        "type": "Polygon", 
        "coordinates": [
          [
            [
              1.400276, 
              43.634614
            ], 
            [
              1.400233, 
              43.634660
            ], 
            [
              1.400137, 
              43.634611
            ], 
            [
              1.400118, 
              43.634607
            ], 
            [
              1.400131, 
              43.634571
            ], 
            [
              1.400276, 
              43.634614
            ], 
            [
              1.400276, 
              43.634614
            ]
          ]
        ]
      }, 
      "id": 2158664754, 
      "properties": {
        "tags": [
          "source=cadastre-dgi-fr source 8c Direction G\u00e9n\u00e9rale des Imp\u00f4ts - Cadastre. Mise \u00e0 jour 8c 2010"
        ], 
        "hierarchy": [
          "woe:airport=12512856", 
          "woe:localadmin=12657137", 
          "woe:county=12597186", 
          "woe:state=7153323", 
          "woe:country=23424819", 
          "woe:planet=1"
        ], 
        "sw_latitude": 43.634571, 
        "osm:node_ids": [
          792473441, 
          792378884, 
          792406164, 
          792438468, 
          792488426, 
          792473441
        ], 
        "ne_longitude": 1.400276, 
        "longitude": 43.634614, 
        "sw_longitude": 1.400118, 
        "woe:placetype": "building", 
        "ne_latitude": 43.634660, 
        "latitude": 1.400196, 
        "iso": "FR", 
        "woe:id": 2158664754, 
        "osm:way_id": 64406430
      }
    }
  ]
}