{
  "type": "FeatureCollection", 
  "features": [
    {
      "geometry": {
        "type": "Polygon", 
        "coordinates": [
          [
            [
              7.604493, 
              51.524493
            ], 
            [
              7.604494, 
              51.524502
            ], 
            [
              7.604395, 
              51.524506
            ], 
            [
              7.604393, 
              51.524494
            ], 
            [
              7.604390, 
              51.524468
            ], 
            [
              7.604387, 
              51.524443
            ], 
            [
              7.604384, 
              51.524417
            ], 
            [
              7.604484, 
              51.524413
            ], 
            [
              7.604493, 
              51.524493
            ], 
            [
              7.604493, 
              51.524493
            ]
          ]
        ]
      }, 
      "id": 2154830103, 
      "properties": {
        "osm:way_id": 55492597, 
        "woe:parent": "23046924", 
        "tags": [
          "addr:housenumber=7", 
          "addr:city=Dortmund", 
          "addr:postcode=44319", 
          "source=HiRes aerial imagery", 
          "addr:country=DE", 
          "addr:street=Emkraft"
        ], 
        "hierarchy": "woe:country=234248829", 
        "parent_woeid": 23046924, 
        "osm:node_ids": [
          697309400, 
          697309401, 
          697309457, 
          697309394, 
          697309392, 
          697309390, 
          697309387, 
          697309398, 
          697309400
        ], 
        "ne_longitude": 7.604494, 
        "longitude": 51.524460, 
        "ne_latitude": 51.524506, 
        "woe:placetype": "building", 
        "sw_longitude": 7.604384, 
        "latitude": 7.604440, 
        "woe:id": 2154830103, 
        "sw_latitude": 51.524413
      }
    }
  ]
}