{
  "type": "FeatureCollection", 
  "features": [
    {
      "geometry": {
        "type": "Polygon", 
        "coordinates": [
          [
            [
              5.252071, 
              52.121339
            ], 
            [
              5.252162, 
              52.121197
            ], 
            [
              5.252066, 
              52.121174
            ], 
            [
              5.251975, 
              52.121316
            ], 
            [
              5.252071, 
              52.121339
            ], 
            [
              5.252071, 
              52.121339
            ]
          ]
        ]
      }, 
      "id": 2155424429, 
      "properties": {
        "osm:way_id": 57911691, 
        "woe:parent": "23195459", 
        "tags": [
          "source=3dShapes", 
          "3dshapes:ggmodelk=0"
        ], 
        "hierarchy": "woe:country=23424909", 
        "parent_woeid": 23195459, 
        "osm:node_ids": [
          718608695, 
          718607524, 
          718606767, 
          718605589, 
          718608695
        ], 
        "ne_longitude": 5.252162, 
        "longitude": 52.121257, 
        "ne_latitude": 52.121339, 
        "woe:placetype": "building", 
        "sw_longitude": 5.251975, 
        "latitude": 5.252069, 
        "woe:id": 2155424429, 
        "sw_latitude": 52.121174
      }
    }
  ]
}