{
  "type": "FeatureCollection", 
  "features": [
    {
      "geometry": {
        "type": "Polygon", 
        "coordinates": [
          [
            [
              2.398653, 
              48.731601
            ], 
            [
              2.398657, 
              48.731575
            ], 
            [
              2.398762, 
              48.731582
            ], 
            [
              2.398757, 
              48.731618
            ], 
            [
              2.398806, 
              48.731621
            ], 
            [
              2.398801, 
              48.731656
            ], 
            [
              2.398647, 
              48.731645
            ], 
            [
              2.398651, 
              48.731615
            ], 
            [
              2.398653, 
              48.731601
            ], 
            [
              2.398653, 
              48.731601
            ]
          ]
        ]
      }, 
      "id": 2162601551, 
      "properties": {
        "osm:way_id": 70864114, 
        "woe:parent": "221441881", 
        "tags": [
          "source=extraction vectorielle v1 cadastre-dgi-fr source 8c Direction G\u00e9n\u00e9rale des Imp\u00f4ts - Cadas. Mise \u00e0 jour 8c 2010"
        ], 
        "hierarchy": "woe:country=234248819", 
        "parent_woeid": 22144181, 
        "osm:node_ids": [
          844738102, 
          844720880, 
          844751621, 
          844804847, 
          844784586, 
          844707741, 
          844716771, 
          844770996, 
          844738102
        ], 
        "ne_longitude": 2.398806, 
        "longitude": 48.731619, 
        "ne_latitude": 48.731656, 
        "woe:placetype": "building", 
        "sw_longitude": 2.398647, 
        "latitude": 2.398719, 
        "woe:id": 2162601551, 
        "sw_latitude": 48.731575
      }
    }
  ]
}