{
  "type": "FeatureCollection", 
  "features": [
    {
      "geometry": {
        "type": "Polygon", 
        "coordinates": [
          [
            [
              -89.711286, 
              40.676880
            ], 
            [
              -89.711433, 
              40.676894
            ], 
            [
              -89.711423, 
              40.676950
            ], 
            [
              -89.711276, 
              40.676936
            ], 
            [
              -89.711286, 
              40.676880
            ], 
            [
              -89.711286, 
              40.676880
            ]
          ]
        ]
      }, 
      "id": 2159722742, 
      "properties": {
        "osm:way_id": 65858770, 
        "woe:parent": "125199882", 
        "tags": [
          "tiger:buildingType=7"
        ], 
        "hierarchy": "woe:country=23424977", 
        "parent_woeid": 12519982, 
        "osm:node_ids": [
          801516833, 
          801510210, 
          801530351, 
          801518860, 
          801516833
        ], 
        "ne_longitude": -89.711276, 
        "longitude": 40.676915, 
        "ne_latitude": 40.676950, 
        "woe:placetype": "building", 
        "sw_longitude": -89.711433, 
        "latitude": -89.711355, 
        "woe:id": 2159722742, 
        "sw_latitude": 40.676880
      }
    }
  ]
}