{
  "type": "FeatureCollection", 
  "features": [
    {
      "geometry": {
        "type": "Polygon", 
        "coordinates": [
          [
            [
              2.187049, 
              48.766325
            ], 
            [
              2.186956, 
              48.766261
            ], 
            [
              2.186997, 
              48.766235
            ], 
            [
              2.187011, 
              48.766244
            ], 
            [
              2.187038, 
              48.766228
            ], 
            [
              2.187064, 
              48.766184
            ], 
            [
              2.187186, 
              48.766213
            ], 
            [
              2.187157, 
              48.766260
            ], 
            [
              2.187140, 
              48.766256
            ], 
            [
              2.187078, 
              48.766295
            ], 
            [
              2.187089, 
              48.766301
            ], 
            [
              2.187049, 
              48.766325
            ], 
            [
              2.187049, 
              48.766325
            ]
          ]
        ]
      }, 
      "id": 2162337618, 
      "properties": {
        "osm:way_id": 70427364, 
        "woe:parent": "56051751", 
        "tags": [
          "note:import-bati=v0.3", 
          "source=cadastre-dgi-fr source 8c Direction G\u00e9n\u00e9rale des Imp\u00f4ts - Cadastre. Mise \u00e0 jour 8c 2010"
        ], 
        "hierarchy": "woe:country=234248819", 
        "parent_woeid": 56051751, 
        "osm:node_ids": [
          840380967, 
          840336597, 
          840382374, 
          840333202, 
          840323323, 
          840347995, 
          840381345, 
          840380615, 
          840382093, 
          840355304, 
          840365916, 
          840380967
        ], 
        "ne_longitude": 2.187186, 
        "longitude": 48.766251, 
        "ne_latitude": 48.766325, 
        "woe:placetype": "building", 
        "sw_longitude": 2.186956, 
        "latitude": 2.187073, 
        "woe:id": 2162337618, 
        "sw_latitude": 48.766184
      }
    }
  ]
}