{
  "type": "FeatureCollection", 
  "features": [
    {
      "geometry": {
        "type": "Polygon", 
        "coordinates": [
          [
            [
              2.311687, 
              48.742926
            ], 
            [
              2.311698, 
              48.742918
            ], 
            [
              2.311731, 
              48.742936
            ], 
            [
              2.311720, 
              48.742944
            ], 
            [
              2.311687, 
              48.742926
            ], 
            [
              2.311687, 
              48.742926
            ]
          ]
        ]
      }, 
      "id": 2167852383, 
      "properties": {
        "woe:parent": "221441881", 
        "tags": [
          "wall=no", 
          "source=extraction vectorielle v1 cadastre-dgi-fr source 8c Direction G\u00e9n\u00e9rale des Imp\u00f4ts - Cadas. Mise \u00e0 jour 8c 2010"
        ], 
        "hierarchy": [
          "woe:airport=221441881", 
          "woe:country=234248819"
        ], 
        "parent_woeid": 22144181, 
        "sw_latitude": 48.742918, 
        "osm:node_ids": [
          946769686, 
          946769687, 
          946769688, 
          946769689, 
          946769686
        ], 
        "ne_longitude": 2.311731, 
        "longitude": 48.742931, 
        "sw_longitude": 2.311687, 
        "woe:placetype": "building", 
        "ne_latitude": 48.742944, 
        "latitude": 2.311710, 
        "woe:id": 2167852383, 
        "osm:way_id": 81262624
      }
    }
  ]
}