{
  "type": "FeatureCollection", 
  "features": [
    {
      "geometry": {
        "type": "Polygon", 
        "coordinates": [
          [
            [
              2.399337, 
              48.714755
            ], 
            [
              2.399282, 
              48.714725
            ], 
            [
              2.399346, 
              48.714671
            ], 
            [
              2.399402, 
              48.714701
            ], 
            [
              2.399366, 
              48.714730
            ], 
            [
              2.399337, 
              48.714755
            ], 
            [
              2.399337, 
              48.714755
            ]
          ]
        ]
      }, 
      "id": 2162208164, 
      "properties": {
        "osm:way_id": 70234035, 
        "woe:parent": "221441881", 
        "tags": [
          "source=extraction vectorielle v1 cadastre-dgi-fr source 8c Direction G\u00e9n\u00e9rale des Imp\u00f4ts - Cadas. Mise \u00e0 jour 8c 2010"
        ], 
        "hierarchy": [
          "woe:airport=22144181", 
          "woe:localadmin=12636789", 
          "woe:county=12597118", 
          "woe:state=7153319", 
          "woe:country=23424819", 
          "woe:planet=1"
        ], 
        "parent_woeid": 22144181, 
        "osm:node_ids": [
          838492689, 
          838477813, 
          838472503, 
          838471544, 
          838547980, 
          838492689
        ], 
        "ne_longitude": 2.399402, 
        "longitude": 48.714713, 
        "sw_longitude": 2.399282, 
        "woe:placetype": "building", 
        "ne_latitude": 48.714755, 
        "latitude": 2.399342, 
        "iso": "FR", 
        "woe:id": 2162208164, 
        "sw_latitude": 48.714671
      }
    }
  ]
}