{
  "type": "FeatureCollection", 
  "features": [
    {
      "geometry": {
        "type": "Polygon", 
        "coordinates": [
          [
            [
              12.612573, 
              55.613096
            ], 
            [
              12.613560, 
              55.613401
            ], 
            [
              12.613053, 
              55.613910
            ], 
            [
              12.612530, 
              55.613755
            ], 
            [
              12.612307, 
              55.613959
            ], 
            [
              12.611860, 
              55.613818
            ], 
            [
              12.612152, 
              55.613542
            ], 
            [
              12.612281, 
              55.613571
            ], 
            [
              12.612513, 
              55.613353
            ], 
            [
              12.612375, 
              55.613309
            ], 
            [
              12.612573, 
              55.613096
            ], 
            [
              12.612573, 
              55.613096
            ]
          ]
        ]
      }, 
      "id": 2147616730, 
      "properties": {
        "osm:way_id": 25699166, 
        "woe:parent": "228851127", 
        "tags": [
          "created_by=Potlatch 0.10"
        ], 
        "hierarchy": "woe:country=23424796", 
        "parent_woeid": 22851127, 
        "osm:node_ids": [
          280180968, 
          280180969, 
          280180970, 
          280180971, 
          280180972, 
          280180929, 
          280180930, 
          280180931, 
          280180932, 
          280180933, 
          280180968
        ], 
        "ne_longitude": 12.613560, 
        "longitude": 55.613556, 
        "ne_latitude": 55.613959, 
        "woe:placetype": "building", 
        "sw_longitude": 12.611860, 
        "latitude": 12.612739, 
        "woe:id": 2147616730, 
        "sw_latitude": 55.613096
      }
    }
  ]
}