{
  "type": "FeatureCollection", 
  "features": [
    {
      "geometry": {
        "type": "Polygon", 
        "coordinates": [
          [
            [
              39.204946, 
              -6.871116
            ], 
            [
              39.204439, 
              -6.871588
            ], 
            [
              39.204325, 
              -6.871465
            ], 
            [
              39.204433, 
              -6.871363
            ], 
            [
              39.204232, 
              -6.871148
            ], 
            [
              39.204573, 
              -6.870830
            ], 
            [
              39.204811, 
              -6.871086
            ], 
            [
              39.204868, 
              -6.871032
            ], 
            [
              39.204946, 
              -6.871116
            ], 
            [
              39.204946, 
              -6.871116
            ]
          ]
        ]
      }, 
      "id": 2150655962, 
      "properties": {
        "tags": [
          "source=yahoo"
        ], 
        "hierarchy": [
          "woe:airport=12518013", 
          "woe:county=56025105", 
          "woe:state=2347374", 
          "woe:country=23424973", 
          "woe:planet=1"
        ], 
        "sw_latitude": -6.871588, 
        "osm:node_ids": [
          595149691, 
          595149417, 
          595149415, 
          595149419, 
          595149431, 
          595149433, 
          595149694, 
          595149696, 
          595149691
        ], 
        "ne_longitude": 39.204946, 
        "longitude": -6.871188, 
        "sw_longitude": 39.204232, 
        "woe:placetype": "building", 
        "ne_latitude": -6.870830, 
        "latitude": 39.204560, 
        "iso": "TZ", 
        "woe:id": 2150655962, 
        "osm:way_id": 46521119
      }
    }
  ]
}