{
  "type": "FeatureCollection", 
  "features": [
    {
      "geometry": {
        "type": "Polygon", 
        "coordinates": [
          [
            [
              2.311233, 
              48.743691
            ], 
            [
              2.311327, 
              48.743618
            ], 
            [
              2.311345, 
              48.743628
            ], 
            [
              2.311366, 
              48.743639
            ], 
            [
              2.311369, 
              48.743637
            ], 
            [
              2.311452, 
              48.743684
            ], 
            [
              2.311372, 
              48.743744
            ], 
            [
              2.311317, 
              48.743713
            ], 
            [
              2.311298, 
              48.743728
            ], 
            [
              2.311233, 
              48.743691
            ], 
            [
              2.311233, 
              48.743691
            ]
          ]
        ]
      }, 
      "id": 2167786525, 
      "properties": {
        "tags": [
          "source=extraction vectorielle v1 cadastre-dgi-fr source 8c Direction G\u00e9n\u00e9rale des Imp\u00f4ts - Cadas. Mise \u00e0 jour 8c 2010"
        ], 
        "hierarchy": [
          "woe:airport=22144181", 
          "woe:localadmin=12636789", 
          "woe:county=12597118", 
          "woe:state=7153319", 
          "woe:country=23424819", 
          "woe:planet=1"
        ], 
        "sw_latitude": 48.743618, 
        "osm:node_ids": [
          945716187, 
          945716189, 
          945716193, 
          945716195, 
          945716196, 
          945716197, 
          945716198, 
          945716199, 
          945716210, 
          945716187
        ], 
        "ne_longitude": 2.311452, 
        "longitude": 48.743684, 
        "sw_longitude": 2.311233, 
        "woe:placetype": "building", 
        "ne_latitude": 48.743744, 
        "latitude": 2.311343, 
        "iso": "FR", 
        "woe:id": 2167786525, 
        "osm:way_id": 81152050
      }
    }
  ]
}