{
  "type": "FeatureCollection", 
  "features": [
    {
      "geometry": {
        "type": "Polygon", 
        "coordinates": [
          [
            [
              37.418098, 
              55.987880
            ], 
            [
              37.418315, 
              55.987916
            ], 
            [
              37.418451, 
              55.987655
            ], 
            [
              37.418234, 
              55.987619
            ], 
            [
              37.418098, 
              55.987880
            ], 
            [
              37.418098, 
              55.987880
            ]
          ]
        ]
      }, 
      "id": 2149543372, 
      "properties": {
        "woe:parent": "125168860", 
        "hierarchy": [
          "woe:airport=125168860", 
          "woe:country=23424936"
        ], 
        "parent_woeid": 12516860, 
        "sw_latitude": 55.987619, 
        "osm:node_ids": [
          495967440, 
          495967444, 
          495967447, 
          495967449, 
          495967440
        ], 
        "ne_longitude": 37.418451, 
        "longitude": 55.987768, 
        "sw_longitude": 37.418098, 
        "woe:placetype": "building", 
        "ne_latitude": 55.987916, 
        "latitude": 37.418275, 
        "woe:id": 2149543372, 
        "osm:way_id": 40794939
      }
    }
  ]
}